[
  {
    "name": null,
    "methods": [
      "HEAD",
      "GET"
    ],
    "paramNames": [],
    "path": "/",
    "regexp": "/^(?:\\/(?=$))?$/",
    "stack": [
      "wrappedController"
    ]
  },
  {
    "name": null,
    "methods": [
      "HEAD",
      "GET"
    ],
    "paramNames": [],
    "path": "/hot",
    "regexp": "/^\\/hot(?:\\/(?=$))?$/",
    "stack": [
      "wrappedController"
    ]
  },
  {
    "name": null,
    "methods": [
      "HEAD",
      "GET"
    ],
    "paramNames": [],
    "path": "/new",
    "regexp": "/^\\/new(?:\\/(?=$))?$/",
    "stack": [
      "wrappedController"
    ]
  },
  {
    "name": null,
    "methods": [
      "HEAD",
      "GET"
    ],
    "paramNames": [
      {
        "name": "id",
        "prefix": "/",
        "delimiter": "/",
        "optional": false,
        "repeat": false,
        "partial": false,
        "asterisk": false,
        "pattern": "[^\\/]+?"
      }
    ],
    "path": "/movie/:id",
    "regexp": "/^\\/movie\\/((?:[^\\/]+?))(?:\\/(?=$))?$/",
    "stack": [
      "wrappedController"
    ]
  },
  {
    "name": null,
    "methods": [
      "HEAD",
      "GET"
    ],
    "paramNames": [
      {
        "name": "movieId",
        "prefix": "/",
        "delimiter": "/",
        "optional": false,
        "repeat": false,
        "partial": false,
        "asterisk": false,
        "pattern": "[^\\/]+?"
      }
    ],
    "path": "/comment/:movieId",
    "regexp": "/^\\/comment\\/((?:[^\\/]+?))(?:\\/(?=$))?$/",
    "stack": [
      "wrappedController"
    ]
  },
  {
    "name": null,
    "methods": [
      "HEAD",
      "GET"
    ],
    "paramNames": [
      {
        "name": "movieId",
        "prefix": "/",
        "delimiter": "/",
        "optional": false,
        "repeat": false,
        "partial": false,
        "asterisk": false,
        "pattern": "[^\\/]+?"
      }
    ],
    "path": "/hot_comment/:movieId",
    "regexp": "/^\\/hot_comment\\/((?:[^\\/]+?))(?:\\/(?=$))?$/",
    "stack": [
      "wrappedController"
    ]
  },
  {
    "name": null,
    "methods": [
      "HEAD",
      "GET"
    ],
    "paramNames": [
      {
        "name": "movieId",
        "prefix": "/",
        "delimiter": "/",
        "optional": false,
        "repeat": false,
        "partial": false,
        "asterisk": false,
        "pattern": "[^\\/]+?"
      }
    ],
    "path": "/stills/:movieId",
    "regexp": "/^\\/stills\\/((?:[^\\/]+?))(?:\\/(?=$))?$/",
    "stack": [
      "wrappedController"
    ]
  },
  {
    "name": null,
    "methods": [
      "HEAD",
      "GET"
    ],
    "paramNames": [
      {
        "name": "movieId",
        "prefix": "/",
        "delimiter": "/",
        "optional": false,
        "repeat": false,
        "partial": false,
        "asterisk": false,
        "pattern": "[^\\/]+?"
      }
    ],
    "path": "/video/:movieId",
    "regexp": "/^\\/video\\/((?:[^\\/]+?))(?:\\/(?=$))?$/",
    "stack": [
      "wrappedController"
    ]
  },
  {
    "name": null,
    "methods": [
      "HEAD",
      "GET"
    ],
    "paramNames": [],
    "path": "/test",
    "regexp": "/^\\/test(?:\\/(?=$))?$/",
    "stack": [
      "wrappedController"
    ]
  },
  {
    "name": null,
    "methods": [
      "POST"
    ],
    "paramNames": [],
    "path": "/test",
    "regexp": "/^\\/test(?:\\/(?=$))?$/",
    "stack": [
      "wrappedController"
    ]
  },
  {
    "name": null,
    "methods": [
      "HEAD",
      "GET"
    ],
    "paramNames": [],
    "path": "/__loader_trace__",
    "regexp": "/^\\/__loader_trace__(?:\\/(?=$))?$/",
    "stack": [
      "wrappedController"
    ]
  }
]